cvt2utf/__init__.py
cvt2utf/main.py
cvt2utf/meta_inf.py
convert2utf-1.3.2.dist-info/LICENSE
convert2utf-1.3.2.dist-info/METADATA
convert2utf-1.3.2.dist-info/WHEEL
convert2utf-1.3.2.dist-info/entry_points.txt
convert2utf-1.3.2.dist-info/top_level.txt
convert2utf-1.3.2.dist-info/RECORD
